{
  "tables": [
    {
      "id": "IyWlAnxxQVjLgMdsFky53",
      "name": "bills",
      "x": -91.5135711745911,
      "y": 100.06326904089346,
      "locked": false,
      "fields": [
        {
          "name": "id",
          "type": "UUID",
          "default": "",
          "check": "",
          "primary": true,
          "unique": true,
          "notNull": true,
          "increment": false,
          "comment": "",
          "id": "-uB4ZOzAli9_UhAUeBBqo",
          "size": "",
          "values": []
        },
        {
          "id": "taxK06F2TbtYP0yqm_jrG",
          "name": "room_id",
          "type": "UUID",
          "default": "",
          "check": "",
          "primary": false,
          "unique": false,
          "notNull": true,
          "increment": false,
          "comment": "",
          "size": "",
          "values": []
        },
        {
          "id": "5Eoc7DLkfOlbwQtlYESKj",
          "name": "month",
          "type": "DATE",
          "default": "",
          "check": "",
          "primary": false,
          "unique": false,
          "notNull": true,
          "increment": false,
          "comment": "",
          "size": "",
          "values": []
        },
        {
          "id": "QNPC85KOH8WInTCXfMBn3",
          "name": "total_amount",
          "type": "DECIMAL",
          "default": "",
          "check": "",
          "primary": false,
          "unique": false,
          "notNull": false,
          "increment": false,
          "comment": "",
          "values": []
        },
        {
          "id": "6Q7Q-m9xeN2KsaHh8MnYq",
          "name": "status",
          "type": "VARCHAR",
          "default": "",
          "check": "",
          "primary": false,
          "unique": false,
          "notNull": true,
          "increment": false,
          "comment": "pending | paid | partial | overdue",
          "size": 255,
          "values": []
        },
        {
          "id": "mZep1UmM0I3eRJCR9mU9N",
          "name": "created_at",
          "type": "TIMESTAMP",
          "default": "",
          "check": "",
          "primary": false,
          "unique": false,
          "notNull": false,
          "increment": false,
          "comment": "",
          "size": "",
          "values": []
        },
        {
          "id": "a7RL4XNWegDIwn7WZaD_n",
          "name": "updated_at",
          "type": "TIMESTAMP",
          "default": "",
          "check": "",
          "primary": false,
          "unique": false,
          "notNull": false,
          "increment": false,
          "comment": "",
          "size": "",
          "values": []
        }
      ],
      "comment": "INDEX (room_id)\nUNIQUE (room_id, month)",
      "indices": [],
      "color": "#175e7a"
    },
    {
      "id": "COX1bYRQSBcOdSNuto0Eg",
      "name": "users",
      "x": 922.3383489348258,
      "y": 519.9297976214823,
      "locked": false,
      "fields": [
        {
          "name": "id",
          "type": "UUID",
          "default": "",
          "check": "",
          "primary": true,
          "unique": true,
          "notNull": true,
          "increment": false,
          "comment": "",
          "id": "UpsQ_qsLMXdSM0sCoINV-",
          "size": "",
          "values": []
        },
        {
          "id": "nCGAuASCDUtqLDOdXUrZZ",
          "name": "name",
          "type": "VARCHAR",
          "default": "",
          "check": "",
          "primary": false,
          "unique": false,
          "notNull": false,
          "increment": false,
          "comment": "",
          "size": 255
        },
        {
          "id": "aVD6ud2z2oaxzwT0ar3_R",
          "name": "phone",
          "type": "VARCHAR",
          "default": "",
          "check": "",
          "primary": false,
          "unique": false,
          "notNull": false,
          "increment": false,
          "comment": "",
          "size": 20,
          "values": []
        },
        {
          "id": "hXJtzoep8VC5nawHozZMB",
          "name": "email",
          "type": "VARCHAR",
          "default": "",
          "check": "",
          "primary": false,
          "unique": false,
          "notNull": false,
          "increment": false,
          "comment": "",
          "size": 255
        },
        {
          "id": "4cgNt2pVhm8oFGHvuwBU5",
          "name": "role",
          "type": "VARCHAR",
          "default": "",
          "check": "",
          "primary": false,
          "unique": false,
          "notNull": false,
          "increment": false,
          "comment": "admin | landlord | tenant",
          "values": [],
          "size": 255
        },
        {
          "id": "YO9B1___xg7OvPSyGv_14",
          "name": "created_at",
          "type": "TIMESTAMP",
          "default": "",
          "check": "",
          "primary": false,
          "unique": false,
          "notNull": false,
          "increment": false,
          "comment": "",
          "size": "",
          "values": []
        }
      ],
      "comment": "INDEX (user_id)",
      "indices": [],
      "color": "#175e7a"
    },
    {
      "id": "nN6Snz5nbeDTGTkdo5Ggn",
      "name": "payments",
      "x": -58.95671185137624,
      "y": 623.5098006516042,
      "locked": false,
      "fields": [
        {
          "name": "id",
          "type": "INT",
          "default": "",
          "check": "",
          "primary": true,
          "unique": true,
          "notNull": true,
          "increment": true,
          "comment": "",
          "id": "q9vY90pf5UwpwXlgVhlvN"
        },
        {
          "id": "AdLuTysT5uy_zQBSUwMGF",
          "name": "bill_id",
          "type": "UUID",
          "default": "",
          "check": "",
          "primary": false,
          "unique": false,
          "notNull": true,
          "increment": false,
          "comment": "",
          "size": "",
          "values": []
        },
        {
          "id": "wfZTNsmJDMwi0kf-VIC_c",
          "name": "amount",
          "type": "DECIMAL",
          "default": "",
          "check": "",
          "primary": false,
          "unique": false,
          "notNull": true,
          "increment": false,
          "comment": "",
          "values": []
        },
        {
          "id": "tr4FBEYt0uadRQsjx-icC",
          "name": "payment_date",
          "type": "TIMESTAMP",
          "default": "",
          "check": "",
          "primary": false,
          "unique": false,
          "notNull": false,
          "increment": false,
          "comment": "",
          "size": "",
          "values": []
        },
        {
          "id": "4Wq6O9rclhygQ1MKbRgQY",
          "name": "method",
          "type": "VARCHAR",
          "default": "",
          "check": "",
          "primary": false,
          "unique": false,
          "notNull": false,
          "increment": false,
          "comment": "",
          "size": 255
        },
        {
          "id": "zgMkofdoLmUZM4H95XY9D",
          "name": "created_at",
          "type": "TIMESTAMP",
          "default": "",
          "check": "",
          "primary": false,
          "unique": false,
          "notNull": false,
          "increment": false,
          "comment": "",
          "size": "",
          "values": []
        },
        {
          "id": "My-bRAzuFxJXRzO3xHcWE",
          "name": "updated_at",
          "type": "TIMESTAMP",
          "default": "",
          "check": "",
          "primary": false,
          "unique": false,
          "notNull": false,
          "increment": false,
          "comment": "",
          "size": "",
          "values": []
        },
        {
          "id": "1cNzQ-gPnvE9ZSqJK2Eyp",
          "name": "status",
          "type": "VARCHAR",
          "default": "",
          "check": "",
          "primary": false,
          "unique": false,
          "notNull": false,
          "increment": false,
          "comment": "success | pending | failed",
          "size": 255
        }
      ],
      "comment": "INDEX (bill_id)",
      "indices": [],
      "color": "#175e7a"
    },
    {
      "id": "oiJFATdhP0Q9n4jyIIWkn",
      "name": "rooms",
      "x": 433.85127221524965,
      "y": 246.03247281854516,
      "locked": false,
      "fields": [
        {
          "name": "id",
          "type": "UUID",
          "default": "",
          "check": "",
          "primary": true,
          "unique": true,
          "notNull": true,
          "increment": false,
          "comment": "",
          "id": "ZVDXJUb6HVBVyKwjPSpNL",
          "size": "",
          "values": []
        },
        {
          "id": "zHAkYheBrf5cSLPvJfNGf",
          "name": "house_id",
          "type": "UUID",
          "default": "",
          "check": "",
          "primary": false,
          "unique": false,
          "notNull": true,
          "increment": false,
          "comment": "",
          "size": "",
          "values": []
        },
        {
          "id": "C4Nme0x_uTo_syD_23H34",
          "name": "name",
          "type": "VARCHAR",
          "default": "",
          "check": "",
          "primary": false,
          "unique": false,
          "notNull": false,
          "increment": false,
          "comment": "",
          "size": 255
        },
        {
          "id": "FPyn-CtzlyZhpaqqkZVJ4",
          "name": "price",
          "type": "DECIMAL",
          "default": "",
          "check": "",
          "primary": false,
          "unique": false,
          "notNull": true,
          "increment": false,
          "comment": "",
          "values": []
        },
        {
          "id": "LeqIXtyB8IcXor-BNMCnr",
          "name": "capacity",
          "type": "INT",
          "default": "",
          "check": "",
          "primary": false,
          "unique": false,
          "notNull": false,
          "increment": false,
          "comment": "",
          "size": "",
          "values": []
        },
        {
          "id": "LxNBrYnaJqhxYzmvg09Pk",
          "name": "status",
          "type": "VARCHAR",
          "default": "",
          "check": "",
          "primary": false,
          "unique": false,
          "notNull": false,
          "increment": false,
          "comment": "available | occupied",
          "size": 255
        }
      ],
      "comment": "INDEX (room_id)",
      "indices": [],
      "color": "#175e7a"
    },
    {
      "id": "QcDQ95waArKpigUvTHIXF",
      "name": "contracts",
      "x": 1052.7767105487117,
      "y": 57.71925291359929,
      "locked": false,
      "fields": [
        {
          "name": "id",
          "type": "INT",
          "default": "",
          "check": "",
          "primary": true,
          "unique": true,
          "notNull": true,
          "increment": true,
          "comment": "",
          "id": "J4WQepImgvHi8_NkOvuBS"
        },
        {
          "id": "bChYQZPnMl5IcbWBB7XLH",
          "name": "room_id",
          "type": "UUID",
          "default": "",
          "check": "",
          "primary": false,
          "unique": false,
          "notNull": true,
          "increment": false,
          "comment": "",
          "size": "",
          "values": []
        },
        {
          "id": "O5ojZo_A97UnY5u4n-fCJ",
          "name": "tenant_id",
          "type": "UUID",
          "default": "",
          "check": "",
          "primary": false,
          "unique": false,
          "notNull": true,
          "increment": false,
          "comment": "",
          "size": "",
          "values": []
        },
        {
          "id": "zkronpsKb-tTGWJ7ayQP_",
          "name": "start_date",
          "type": "TIMESTAMP",
          "default": "",
          "check": "",
          "primary": false,
          "unique": false,
          "notNull": false,
          "increment": false,
          "comment": "",
          "size": "",
          "values": []
        },
        {
          "id": "m0oZt-Qi4R508QF5kiLMc",
          "name": "end_date",
          "type": "TIMESTAMP",
          "default": "",
          "check": "",
          "primary": false,
          "unique": false,
          "notNull": false,
          "increment": false,
          "comment": "",
          "size": "",
          "values": []
        },
        {
          "id": "AWrCzPdIV-U5_knC6A4Yi",
          "name": "status",
          "type": "VARCHAR",
          "default": "",
          "check": "",
          "primary": false,
          "unique": false,
          "notNull": false,
          "increment": false,
          "comment": "status: active | expired | terminated",
          "size": 255
        },
        {
          "id": "Iu8p787SZSHOKjHJIId2n",
          "name": "deposit_amount",
          "type": "DECIMAL",
          "default": "",
          "check": "",
          "primary": false,
          "unique": false,
          "notNull": false,
          "increment": false,
          "comment": "",
          "values": []
        },
        {
          "id": "xsT3doA8OA7kd7-XAINod",
          "name": "created_at",
          "type": "TIMESTAMP",
          "default": "",
          "check": "",
          "primary": false,
          "unique": false,
          "notNull": false,
          "increment": false,
          "comment": "",
          "size": "",
          "values": []
        },
        {
          "id": "1bW7-mKJ5SHrXIKTUM6O2",
          "name": "updated_at",
          "type": "TIMESTAMP",
          "default": "",
          "check": "",
          "primary": false,
          "unique": false,
          "notNull": false,
          "increment": false,
          "comment": "",
          "size": "",
          "values": []
        }
      ],
      "comment": "",
      "indices": [],
      "color": "#175e7a"
    },
    {
      "id": "wfZwVpHkpNihQofGZjt6q",
      "name": "houses",
      "x": 368.13416123630213,
      "y": 871.9075084665852,
      "locked": false,
      "fields": [
        {
          "name": "id",
          "type": "UUID",
          "default": "",
          "check": "",
          "primary": true,
          "unique": true,
          "notNull": true,
          "increment": false,
          "comment": "",
          "id": "0IhbQVqiqk9GNo9CtDrQe",
          "size": "",
          "values": []
        },
        {
          "id": "WU75oEf2tze36n0Cln0mq",
          "name": "landlord_id",
          "type": "UUID",
          "default": "",
          "check": "",
          "primary": false,
          "unique": false,
          "notNull": false,
          "increment": false,
          "comment": "",
          "size": "",
          "values": []
        },
        {
          "id": "XN7LLGnmj9x42lqpELdWb",
          "name": "name",
          "type": "VARCHAR",
          "default": "",
          "check": "",
          "primary": false,
          "unique": false,
          "notNull": false,
          "increment": false,
          "comment": "",
          "size": 255
        },
        {
          "id": "4iq72T-Do-3LslI8OMzqx",
          "name": "address",
          "type": "VARCHAR",
          "default": "",
          "check": "",
          "primary": false,
          "unique": false,
          "notNull": false,
          "increment": false,
          "comment": "",
          "size": 255
        },
        {
          "id": "kho6-0UOij19mQSg4Wfgo",
          "name": "created_at",
          "type": "TIMESTAMP",
          "default": "",
          "check": "",
          "primary": false,
          "unique": false,
          "notNull": false,
          "increment": false,
          "comment": "",
          "size": "",
          "values": []
        }
      ],
      "comment": "",
      "indices": [],
      "color": "#175e7a"
    },
    {
      "id": "i-9SlPHPT9yWKvrnkivdc",
      "name": "room_users",
      "x": 451.6616108674722,
      "y": -170.15644312765707,
      "locked": false,
      "fields": [
        {
          "name": "id",
          "type": "UUID",
          "default": "",
          "check": "",
          "primary": true,
          "unique": true,
          "notNull": true,
          "increment": false,
          "comment": "",
          "id": "7OS3MeRnik39gGORihGlM",
          "size": "",
          "values": []
        },
        {
          "id": "b5yhnQLYJWKC_GPeKu0Ls",
          "name": "room_id",
          "type": "UUID",
          "default": "",
          "check": "",
          "primary": false,
          "unique": false,
          "notNull": true,
          "increment": false,
          "comment": "",
          "size": "",
          "values": []
        },
        {
          "id": "q3Z1OrCX0us_XqObWOuwm",
          "name": "user_id",
          "type": "UUID",
          "default": "",
          "check": "",
          "primary": false,
          "unique": false,
          "notNull": true,
          "increment": false,
          "comment": "",
          "size": "",
          "values": []
        },
        {
          "id": "UpBUf6NxRUQrWXwqZmwMY",
          "name": "start_date",
          "type": "TIMESTAMP",
          "default": "",
          "check": "",
          "primary": false,
          "unique": false,
          "notNull": false,
          "increment": false,
          "comment": "",
          "size": "",
          "values": []
        },
        {
          "id": "lDxqijIalLbfuUuvzUa6M",
          "name": "end_date",
          "type": "TIMESTAMP",
          "default": "",
          "check": "",
          "primary": false,
          "unique": false,
          "notNull": false,
          "increment": false,
          "comment": "",
          "size": "",
          "values": []
        },
        {
          "id": "mxeopkfAjc6jZPki42qp_",
          "name": "created_at",
          "type": "TIMESTAMP",
          "default": "",
          "check": "",
          "primary": false,
          "unique": false,
          "notNull": false,
          "increment": false,
          "comment": "",
          "size": "",
          "values": []
        },
        {
          "id": "3Idu_QDW9Id-fSmoxNe68",
          "name": "updated_at",
          "type": "TIMESTAMP",
          "default": "",
          "check": "",
          "primary": false,
          "unique": false,
          "notNull": false,
          "increment": false,
          "comment": "",
          "size": "",
          "values": []
        }
      ],
      "comment": "",
      "indices": [],
      "color": "#175e7a"
    },
    {
      "id": "E2yItr0wCLbQ_70q4vmIs",
      "name": "meter_readings",
      "x": 799.8558786193101,
      "y": 949.4374934380816,
      "locked": false,
      "fields": [
        {
          "name": "id",
          "type": "INT",
          "default": "",
          "check": "",
          "primary": true,
          "unique": true,
          "notNull": true,
          "increment": true,
          "comment": "",
          "id": "Xv427I2HJphw8SJDnd8o7"
        },
        {
          "id": "IFwNiVTTkFFfa-WK9egim",
          "name": "room_id",
          "type": "UUID",
          "default": "",
          "check": "",
          "primary": false,
          "unique": false,
          "notNull": true,
          "increment": false,
          "comment": "",
          "size": "",
          "values": []
        },
        {
          "id": "bW7mDWGr-ej45AnapF9E2",
          "name": "type",
          "type": "VARCHAR",
          "default": "",
          "check": "",
          "primary": false,
          "unique": false,
          "notNull": true,
          "increment": false,
          "comment": "electric | water",
          "size": 255
        },
        {
          "id": "LGQ2L38c4q9GvENF8Pr1R",
          "name": "previous_reading",
          "type": "DECIMAL",
          "default": "",
          "check": "",
          "primary": false,
          "unique": false,
          "notNull": false,
          "increment": false,
          "comment": ""
        },
        {
          "id": "l7nzwmQg4E110tD6yZ0oE",
          "name": "current_reading",
          "type": "DECIMAL",
          "default": "",
          "check": "",
          "primary": false,
          "unique": false,
          "notNull": false,
          "increment": false,
          "comment": ""
        },
        {
          "id": "3fo2JOLydd4a6jVAx44Os",
          "name": "month",
          "type": "DATE",
          "default": "",
          "check": "",
          "primary": false,
          "unique": false,
          "notNull": true,
          "increment": false,
          "comment": "",
          "size": "",
          "values": []
        }
      ],
      "comment": "UNIQUE (room_id, type, month)\n",
      "indices": [],
      "color": "#175e7a"
    },
    {
      "id": "awulanGYbLvJXXiIQzPv3",
      "name": "bill_items",
      "x": -143.3879907029977,
      "y": -330.53113862616595,
      "locked": false,
      "fields": [
        {
          "name": "id",
          "type": "UUID",
          "default": "",
          "check": "",
          "primary": true,
          "unique": true,
          "notNull": true,
          "increment": false,
          "comment": "",
          "id": "5hO_iW7oF-rD3xqcsYmXy",
          "size": "",
          "values": []
        },
        {
          "id": "Fhcj2RnoF6Fpzdu4B8w_T",
          "name": "bill_id",
          "type": "UUID",
          "default": "",
          "check": "",
          "primary": false,
          "unique": false,
          "notNull": true,
          "increment": false,
          "comment": "",
          "size": "",
          "values": []
        },
        {
          "id": "sNDdlqXGvqkaSQByeZgaK",
          "name": "type",
          "type": "VARCHAR",
          "default": "",
          "check": "",
          "primary": false,
          "unique": false,
          "notNull": false,
          "increment": false,
          "comment": "electric | water | rent | service",
          "size": 255
        },
        {
          "id": "V9E1qK6B54Jx6V6RXaoNp",
          "name": "amount",
          "type": "DECIMAL",
          "default": "",
          "check": "",
          "primary": false,
          "unique": false,
          "notNull": false,
          "increment": false,
          "comment": "",
          "values": []
        },
        {
          "id": "6P-irBX4qB2ghMKIydlcT",
          "name": "unit_price",
          "type": "DECIMAL",
          "default": "",
          "check": "",
          "primary": false,
          "unique": false,
          "notNull": false,
          "increment": false,
          "comment": "",
          "values": []
        },
        {
          "id": "e4aBlagmmuwPCikQgf60I",
          "name": "quantity",
          "type": "INT",
          "default": "",
          "check": "",
          "primary": false,
          "unique": false,
          "notNull": false,
          "increment": false,
          "comment": "",
          "size": "",
          "values": []
        }
      ],
      "comment": "",
      "indices": [],
      "color": "#175e7a"
    },
    {
      "id": "Rka5-FxanurytMxYRapeH",
      "name": "notifications",
      "x": 1486.2888540126621,
      "y": 423.2225192449268,
      "locked": false,
      "fields": [
        {
          "name": "id",
          "type": "INT",
          "default": "",
          "check": "",
          "primary": true,
          "unique": true,
          "notNull": true,
          "increment": true,
          "comment": "",
          "id": "xsC5ablN8OoRLnRyPw_i_"
        },
        {
          "id": "aqYLeZ8Re53FS1K4mg5VZ",
          "name": "user_id",
          "type": "UUID",
          "default": "",
          "check": "",
          "primary": false,
          "unique": false,
          "notNull": true,
          "increment": false,
          "comment": "",
          "size": "",
          "values": []
        },
        {
          "id": "750ZunT4fU8q4dzRK8s0o",
          "name": "title",
          "type": "VARCHAR",
          "default": "",
          "check": "",
          "primary": false,
          "unique": false,
          "notNull": false,
          "increment": false,
          "comment": "",
          "size": 255
        },
        {
          "id": "21bGvjbyr1Hqv-NvA-c-g",
          "name": "content",
          "type": "TEXT",
          "default": "",
          "check": "",
          "primary": false,
          "unique": false,
          "notNull": false,
          "increment": false,
          "comment": "",
          "size": 65535
        },
        {
          "id": "5Dl-TZQL-mWL5zY7dFQJj",
          "name": "is_read",
          "type": "BOOLEAN",
          "default": "",
          "check": "",
          "primary": false,
          "unique": false,
          "notNull": false,
          "increment": false,
          "comment": "",
          "size": "",
          "values": []
        },
        {
          "id": "7wZ-SLJX_eGZ-nuUQ8m1h",
          "name": "created_at",
          "type": "TIMESTAMP",
          "default": "",
          "check": "",
          "primary": false,
          "unique": false,
          "notNull": false,
          "increment": false,
          "comment": "",
          "size": "",
          "values": []
        },
        {
          "id": "OdadGDLAhjaFoYj36wDbR",
          "name": "type",
          "type": "VARCHAR",
          "default": "",
          "check": "",
          "primary": false,
          "unique": false,
          "notNull": false,
          "increment": false,
          "comment": "bill | system | maintenance",
          "size": 255
        }
      ],
      "comment": "",
      "indices": [],
      "color": "#175e7a"
    },
    {
      "id": "701Fc-705l3VZQquu2W_P",
      "name": "maintenance_requests",
      "x": -350.10536813265094,
      "y": 518.4029045240997,
      "locked": false,
      "fields": [
        {
          "name": "id",
          "type": "INT",
          "default": "",
          "check": "",
          "primary": true,
          "unique": true,
          "notNull": true,
          "increment": true,
          "comment": "",
          "id": "dvXuaXkpZFJmDoEkVfDa1"
        },
        {
          "id": "nA-CaSgh1wyS807Az0ynF",
          "name": "room_id",
          "type": "UUID",
          "default": "",
          "check": "",
          "primary": false,
          "unique": false,
          "notNull": true,
          "increment": false,
          "comment": "",
          "size": "",
          "values": []
        },
        {
          "id": "_XeIkhN6u2-o2Td0XGXJo",
          "name": "tenant_id",
          "type": "UUID",
          "default": "",
          "check": "",
          "primary": false,
          "unique": false,
          "notNull": true,
          "increment": false,
          "comment": "",
          "size": "",
          "values": []
        },
        {
          "id": "Tay-zgqB3J40hKyp43f4y",
          "name": "title",
          "type": "VARCHAR",
          "default": "",
          "check": "",
          "primary": false,
          "unique": false,
          "notNull": false,
          "increment": false,
          "comment": "",
          "size": 255
        },
        {
          "id": "QVNtaa4VHlgvpsPWpVpxo",
          "name": "description",
          "type": "TEXT",
          "default": "",
          "check": "",
          "primary": false,
          "unique": false,
          "notNull": false,
          "increment": false,
          "comment": "",
          "size": 65535
        },
        {
          "id": "Dsj3pG4I9fZZPma7q79dw",
          "name": "status",
          "type": "VARCHAR",
          "default": "",
          "check": "",
          "primary": false,
          "unique": false,
          "notNull": false,
          "increment": false,
          "comment": "pending | in_progress | done | cancelled",
          "size": 255,
          "values": []
        },
        {
          "id": "iV4CVj0j1IJkzXEFoP_pj",
          "name": "created_at",
          "type": "TIMESTAMP",
          "default": "",
          "check": "",
          "primary": false,
          "unique": false,
          "notNull": false,
          "increment": false,
          "comment": "",
          "size": "",
          "values": []
        },
        {
          "id": "_uuWTRHtqEytLDtErnGY0",
          "name": "updated_at",
          "type": "TIMESTAMP",
          "default": "",
          "check": "",
          "primary": false,
          "unique": false,
          "notNull": false,
          "increment": false,
          "comment": "",
          "size": "",
          "values": []
        }
      ],
      "comment": "",
      "indices": [],
      "color": "#175e7a"
    },
    {
      "id": "s3Bg-wpALJwApkUHIuFYh",
      "name": "houses_staff",
      "x": 104.16728465518804,
      "y": 1199.0693884725824,
      "locked": false,
      "fields": [
        {
          "name": "id",
          "type": "INT",
          "default": "",
          "check": "",
          "primary": true,
          "unique": true,
          "notNull": true,
          "increment": true,
          "comment": "",
          "id": "bsKe1Chy-xYIMx5-UPQDu"
        },
        {
          "id": "3bRuWPfpEwMOxLeYURMK2",
          "name": "house_id",
          "type": "UUID",
          "default": "",
          "check": "",
          "primary": false,
          "unique": false,
          "notNull": true,
          "increment": false,
          "comment": "",
          "size": "",
          "values": []
        },
        {
          "id": "UcK4s0FJOKOdX9ZF7St_U",
          "name": "user_id",
          "type": "UUID",
          "default": "",
          "check": "",
          "primary": false,
          "unique": false,
          "notNull": true,
          "increment": false,
          "comment": "",
          "size": "",
          "values": []
        },
        {
          "id": "kkma10kQALVQAK9qrsZEl",
          "name": "role",
          "type": "VARCHAR",
          "default": "",
          "check": "",
          "primary": false,
          "unique": false,
          "notNull": false,
          "increment": false,
          "comment": "manager | security | ...",
          "size": 255
        }
      ],
      "comment": "",
      "indices": [],
      "color": "#175e7a"
    }
  ],
  "relationships": [
    {
      "startTableId": "wfZwVpHkpNihQofGZjt6q",
      "startFieldId": "WU75oEf2tze36n0Cln0mq",
      "endTableId": "COX1bYRQSBcOdSNuto0Eg",
      "endFieldId": "UpsQ_qsLMXdSM0sCoINV-",
      "cardinality": "many_to_one",
      "updateConstraint": "No action",
      "deleteConstraint": "No action",
      "name": "fk_houses_landlord_id_users",
      "id": "U2xXktlOvnJYhAzYj_0Ah"
    },
    {
      "startTableId": "wfZwVpHkpNihQofGZjt6q",
      "startFieldId": "0IhbQVqiqk9GNo9CtDrQe",
      "endTableId": "oiJFATdhP0Q9n4jyIIWkn",
      "endFieldId": "zHAkYheBrf5cSLPvJfNGf",
      "cardinality": "one_to_many",
      "updateConstraint": "No action",
      "deleteConstraint": "No action",
      "name": "fk_houses_id_rooms",
      "id": "FbIblWxsYQAISwsxfL4gy"
    },
    {
      "startTableId": "i-9SlPHPT9yWKvrnkivdc",
      "startFieldId": "b5yhnQLYJWKC_GPeKu0Ls",
      "endTableId": "oiJFATdhP0Q9n4jyIIWkn",
      "endFieldId": "ZVDXJUb6HVBVyKwjPSpNL",
      "cardinality": "many_to_one",
      "updateConstraint": "No action",
      "deleteConstraint": "No action",
      "name": "fk_room_users_room_id_rooms",
      "id": "l_jAoNAHlcGkUCyi_2Z7_"
    },
    {
      "startTableId": "i-9SlPHPT9yWKvrnkivdc",
      "startFieldId": "q3Z1OrCX0us_XqObWOuwm",
      "endTableId": "COX1bYRQSBcOdSNuto0Eg",
      "endFieldId": "UpsQ_qsLMXdSM0sCoINV-",
      "cardinality": "one_to_many",
      "updateConstraint": "No action",
      "deleteConstraint": "No action",
      "name": "fk_room_users_user_id_users",
      "id": "cJ8b-drj9c_Yd45s1Rjjz"
    },
    {
      "startTableId": "IyWlAnxxQVjLgMdsFky53",
      "startFieldId": "taxK06F2TbtYP0yqm_jrG",
      "endTableId": "oiJFATdhP0Q9n4jyIIWkn",
      "endFieldId": "ZVDXJUb6HVBVyKwjPSpNL",
      "cardinality": "many_to_one",
      "updateConstraint": "No action",
      "deleteConstraint": "No action",
      "name": "fk_bills_room_id_rooms",
      "id": "dnSkeCtzFMUhqGezChSuL"
    },
    {
      "startTableId": "nN6Snz5nbeDTGTkdo5Ggn",
      "startFieldId": "AdLuTysT5uy_zQBSUwMGF",
      "endTableId": "IyWlAnxxQVjLgMdsFky53",
      "endFieldId": "-uB4ZOzAli9_UhAUeBBqo",
      "cardinality": "many_to_one",
      "updateConstraint": "No action",
      "deleteConstraint": "No action",
      "name": "fk_payments_bill_id_bills",
      "id": "SU_DRszXDL7ag0xGXBTlS"
    },
    {
      "startTableId": "QcDQ95waArKpigUvTHIXF",
      "startFieldId": "bChYQZPnMl5IcbWBB7XLH",
      "endTableId": "oiJFATdhP0Q9n4jyIIWkn",
      "endFieldId": "ZVDXJUb6HVBVyKwjPSpNL",
      "cardinality": "many_to_one",
      "updateConstraint": "No action",
      "deleteConstraint": "No action",
      "name": "fk_contracts_room_id_rooms",
      "id": "GzX2eRDb2dc5j3p2ul941"
    },
    {
      "startTableId": "QcDQ95waArKpigUvTHIXF",
      "startFieldId": "O5ojZo_A97UnY5u4n-fCJ",
      "endTableId": "COX1bYRQSBcOdSNuto0Eg",
      "endFieldId": "UpsQ_qsLMXdSM0sCoINV-",
      "cardinality": "many_to_one",
      "updateConstraint": "No action",
      "deleteConstraint": "No action",
      "name": "fk_contracts_tenant_id_users",
      "id": "v3nqZoXV_Q1GGNPqAYdx5"
    },
    {
      "startTableId": "E2yItr0wCLbQ_70q4vmIs",
      "startFieldId": "IFwNiVTTkFFfa-WK9egim",
      "endTableId": "oiJFATdhP0Q9n4jyIIWkn",
      "endFieldId": "ZVDXJUb6HVBVyKwjPSpNL",
      "cardinality": "many_to_one",
      "updateConstraint": "No action",
      "deleteConstraint": "No action",
      "name": "fk_meter_readings_room_id_rooms",
      "id": "GfoSoZLvV3vcYKLVmG6nw"
    },
    {
      "startTableId": "awulanGYbLvJXXiIQzPv3",
      "startFieldId": "Fhcj2RnoF6Fpzdu4B8w_T",
      "endTableId": "IyWlAnxxQVjLgMdsFky53",
      "endFieldId": "-uB4ZOzAli9_UhAUeBBqo",
      "cardinality": "many_to_one",
      "updateConstraint": "No action",
      "deleteConstraint": "No action",
      "name": "fk_bill_items_bill_id_bills",
      "id": "Ww7bmgF323BUcSeyY1tJU"
    },
    {
      "startTableId": "Rka5-FxanurytMxYRapeH",
      "startFieldId": "aqYLeZ8Re53FS1K4mg5VZ",
      "endTableId": "COX1bYRQSBcOdSNuto0Eg",
      "endFieldId": "UpsQ_qsLMXdSM0sCoINV-",
      "cardinality": "many_to_one",
      "updateConstraint": "No action",
      "deleteConstraint": "No action",
      "name": "fk_notifications_user_id_users",
      "id": "tocWiGm4EPGRYs9pYnQK1"
    },
    {
      "startTableId": "701Fc-705l3VZQquu2W_P",
      "startFieldId": "nA-CaSgh1wyS807Az0ynF",
      "endTableId": "oiJFATdhP0Q9n4jyIIWkn",
      "endFieldId": "ZVDXJUb6HVBVyKwjPSpNL",
      "cardinality": "many_to_one",
      "updateConstraint": "No action",
      "deleteConstraint": "No action",
      "name": "fk_maintenance_requests_room_id_rooms",
      "id": "MYDGAfylqiN8XqN2vG8R8"
    },
    {
      "startTableId": "701Fc-705l3VZQquu2W_P",
      "startFieldId": "_XeIkhN6u2-o2Td0XGXJo",
      "endTableId": "COX1bYRQSBcOdSNuto0Eg",
      "endFieldId": "UpsQ_qsLMXdSM0sCoINV-",
      "cardinality": "many_to_one",
      "updateConstraint": "No action",
      "deleteConstraint": "No action",
      "name": "fk_maintenance_requests_tenant_id_users",
      "id": "8GhnHiR_aCqiU3xJlCYBH"
    },
    {
      "startTableId": "s3Bg-wpALJwApkUHIuFYh",
      "startFieldId": "3bRuWPfpEwMOxLeYURMK2",
      "endTableId": "wfZwVpHkpNihQofGZjt6q",
      "endFieldId": "0IhbQVqiqk9GNo9CtDrQe",
      "cardinality": "many_to_one",
      "updateConstraint": "No action",
      "deleteConstraint": "No action",
      "name": "fk_houses_staff_house_id_houses",
      "id": "HNJIDX0ZL-M_fvID7x0iO"
    },
    {
      "startTableId": "s3Bg-wpALJwApkUHIuFYh",
      "startFieldId": "UcK4s0FJOKOdX9ZF7St_U",
      "endTableId": "COX1bYRQSBcOdSNuto0Eg",
      "endFieldId": "UpsQ_qsLMXdSM0sCoINV-",
      "cardinality": "many_to_one",
      "updateConstraint": "No action",
      "deleteConstraint": "No action",
      "name": "fk_houses_staff_user_id_users",
      "id": "H4oWrlUd2ItL-bNXVyu6t"
    }
  ],
  "notes": [],
  "subjectAreas": [],
  "database": "generic",
  "types": [],
  "title": "roomio"
}